mysql/__init__.py
sqlpd/__init__.py
sqlpd/src/connection.py
sqlpd/src/mysql/__init__.py
sqlpd/src/mysql/connector/__init__.py
sqlpd/src/mysql/connector/abstracts.py
sqlpd/src/mysql/connector/authentication.py
sqlpd/src/mysql/connector/catch23.py
sqlpd/src/mysql/connector/charsets.py
sqlpd/src/mysql/connector/connection.py
sqlpd/src/mysql/connector/connection_cext.py
sqlpd/src/mysql/connector/constants.py
sqlpd/src/mysql/connector/conversion.py
sqlpd/src/mysql/connector/cursor.py
sqlpd/src/mysql/connector/cursor_cext.py
sqlpd/src/mysql/connector/custom_types.py
sqlpd/src/mysql/connector/dbapi.py
sqlpd/src/mysql/connector/errorcode.py
sqlpd/src/mysql/connector/errors.py
sqlpd/src/mysql/connector/network.py
sqlpd/src/mysql/connector/optionfiles.py
sqlpd/src/mysql/connector/pooling.py
sqlpd/src/mysql/connector/protocol.py
sqlpd/src/mysql/connector/utils.py
sqlpd/src/mysql/connector/version.py
sqlpd/src/mysql/connector/django/__init__.py
sqlpd/src/mysql/connector/django/base.py
sqlpd/src/mysql/connector/django/client.py
sqlpd/src/mysql/connector/django/compiler.py
sqlpd/src/mysql/connector/django/creation.py
sqlpd/src/mysql/connector/django/features.py
sqlpd/src/mysql/connector/django/introspection.py
sqlpd/src/mysql/connector/django/operations.py
sqlpd/src/mysql/connector/django/schema.py
sqlpd/src/mysql/connector/django/validation.py
sqlpd/src/mysql/connector/fabric/__init__.py
sqlpd/src/mysql/connector/fabric/balancing.py
sqlpd/src/mysql/connector/fabric/caching.py
sqlpd/src/mysql/connector/fabric/connection.py
sqlpd/src/mysql/connector/locales/__init__.py
sqlpd/src/mysql/connector/locales/eng/__init__.py
sqlpd/src/mysql/connector/locales/eng/client_error.py
sqlpd-4.0.0.dist-info/LICENSE
sqlpd-4.0.0.dist-info/METADATA
sqlpd-4.0.0.dist-info/WHEEL
sqlpd-4.0.0.dist-info/top_level.txt
sqlpd-4.0.0.dist-info/RECORD
