Metadata-Version: 2.1
Name: sqlpd
Version: 4.0.0
Summary: return a path information
Author: Moses Dastmard
License: UNKNOWN
Platform: UNKNOWN
License-File: LICENSE
